Workbook

Sheet Cover
B2: DISCOUNTED CASH FLOW MODEL
B4: UNILEVER PLC (ULVR.L · LSE)
B7: Analyst: | D7: Roman Falla
B8: Degree: | D8: BSc Economics & Management, University of Bristol
B9: Date: | D9: May 2026
B10: Model Version: | D10: 1.0
B11: Currency: | D11: GBP (£mm unless stated)
B12: Projection Period: | D12: FY2025E – FY2029E (5-year)
B13: Valuation Method: | D13: Unlevered DCF + Gordon Growth Terminal Value
B14: Cross-check: | D14: EV/EBITDA Exit Multiple
B17: DISCLAIMER: This model is built for educational and portfolio purposes only. It does not constitute investment advice. All figures are based on publicly available information and analyst estimates.

Sheet Assumptions
A1: UNILEVER PLC (ULVR.L) — DCF VALUATION MODEL
A2: Roman Falla · BSc Economics & Management, University of Bristol · May 2026
A4: KEY ASSUMPTIONS
A5: Assumption | B5: 2025 | C5: 2026 | D5: 2027 | E5: 2028 | F5: 2029
A6: Revenue Growth Rate (%) | B6: 0.04 | C6: 0.045 | D6: 0.048 | E6: 0.05 | F6: 0.05
A7: EBIT Margin (%) | B7: 0.16 | C7: 0.162 | D7: 0.165 | E7: 0.167 | F7: 0.17
A8: Tax Rate (%) | B8: 0.25 | C8: 0.25 | D8: 0.25 | E8: 0.25 | F8: 0.25
A9: D&A as % of Revenue (%) | B9: 0.04 | C9: 0.04 | D9: 0.039 | E9: 0.039 | F9: 0.038
A10: Capex as % of Revenue (%) | B10: 0.035 | C10: 0.035 | D10: 0.034 | E10: 0.034 | F10: 0.033
A11: Change in NWC as % Rev (%) | B11: 0.01 | C11: 0.01 | D11: 0.01 | E11: 0.01 | F11: 0.01
A13: WACC ASSUMPTIONS
A14: Risk-Free Rate (%) | B14: 0.045 | C14: Source: UK 10Y Gilt yield, May 2026
A15: Equity Risk Premium (%) | B15: 0.05 | C15: Source: Damodaran, Jan 2026
A16: Beta | B16: 0.65 | C16: Source: Bloomberg Terminal, 5Y monthly
A17: Cost of Equity (%) | B17: =B15+B16*B17 | C17: =Rf + Beta x ERP
A18: Cost of Debt (pre-tax) (%) | B18: 0.04 | C18: Source: Unilever FY2024 Annual Report
A19: Tax Rate (%) | B19: 0.25 | C19: Consistent with income statement
A20: Cost of Debt (post-tax) (%) | B20: =B18*(1-B19) | C20: =Kd x (1 - Tax Rate)
A21: Debt / (Debt + Equity) | B21: 0.3 | C21: Source: Unilever FY2024 Balance Sheet
A22: Equity / (Debt + Equity) | B22: =1-B21 | C22: =1 - D/(D+E)
A23: WACC (%) | B23: =B18*(1-B19)*B21+B22*B24 | C23: =Ke x E/V + Kd(1-t) x D/V
A25: TERMINAL VALUE ASSUMPTIONS
A26: Terminal Growth Rate (%) | B26: 0.025 | C26: Gordon Growth Model; below long-run UK nominal GDP
A27: Exit EV/EBITDA Multiple (cross-check) | B27: 12
A29: SHARE & BALANCE SHEET DATA
A30: Shares Outstanding (mm) | B30: 2587 | C30: Source: Unilever FY2024 Annual Report
A31: Net Debt (£mm) | B31: 9800 | C31: Source: Unilever FY2024 Balance Sheet
A32: Current Share Price (£) | B32: 38.5 | C32: Source: LSE, May 2026

Sheet Income Statement & FCF
A1: INCOME STATEMENT & FREE CASH FLOW BRIDGE (£mm)
A2: (£mm) | B2: 2020 | C2: 2021 | D2: 2022 | E2: 2023 | F2: 2024 | G2: 2025 | H2: 2026 | I2: 2027 | J2: 2028 | K2: 2029
A3: REVENUE
A4: Revenue | B4: 52444 | C4: 51980 | D4: 60073 | E4: 59955 | F4: 59949 | G4: =F4*(1+Assumptions!B6) | H4: =G4*(1+Assumptions!C6) | I4: =H4*(1+Assumptions!D6) | J4: =I4*(1+Assumptions!E6) | K4: =J4*(1+Assumptions!F6)
A5: Revenue Growth (%) | B5: - | C5: =(C4-B4)/B4 | D5: =(D4-C4)/C4 | E5: =(E4-D4)/D4 | F5: =(F4-E4)/E4 | G5: =(G4-F4)/F4 | H5: =(H4-G4)/G4 | I5: =(I4-H4)/H4 | J5: =(J4-I4)/I4 | K5: =(K4-J4)/J4
A6: PROFITABILITY
A7: EBIT | B7: 8474 | C7: 8244 | D7: 9746 | E7: 9356 | F7: 9577 | G7: =G4*Assumptions!B7 | H7: =H4*Assumptions!C7 | I7: =I4*Assumptions!D7 | J7: =J4*Assumptions!E7 | K7: =K4*Assumptions!F7
A8: EBIT Margin (%) | B8: =B7/B4 | C8: =C7/C4 | D8: =D7/D4 | E8: =E7/E4 | F8: =F7/F4 | G8: =G7/G4 | H8: =H7/H4 | I8: =I7/I4 | ... K8: =K7/K4
A9: Tax | B9: =B7*0.25 | C9: =C7*0.25 | D9: =D7*0.25 | E9: =E7*0.25 | F9: =F7*0.25 | G9: =G7*Assumptions!B8 | H9: =H7*Assumptions!C8 | I9: =I7*Assumptions!D8 | J9: =J7*Assumptions!E8 | K9: =K7*Assumptions!F8
A10: NOPAT (EBIT after tax) | B10: =B7-B9 | C10: =C7-C9 | D10: =D7-D9 | E10: =E7-E9 | F10: =F7-F9 | G10: =G7-G9 | H10: =H7-H9 | I10: =I7-I9 | ... K10: =K7-K9
A11: FREE CASH FLOW BRIDGE
A12: D&A | B12: 1900 | C12: 1950 | D12: 2100 | E12: 2150 | F12: 2180 | G12: =G4*Assumptions!B9 | H12: =H4*Assumptions!C9 | I12: =I4*Assumptions!D9 | J12: =J4*Assumptions!E9 | K12: =K4*Assumptions!F9
A13: Capex | B13: -1700 | C13: -1650 | D13: -2000 | E13: -2050 | F13: -2100 | G13: =-G4*Assumptions!B10 | H13: =-H4*Assumptions!C10 | I13: =-I4*Assumptions!D10 | J13: =-J4*Assumptions!E10 | K13: =-K4*Assumptions!F10
A14: Change in NWC | B14: -500 | C14: -400 | D14: -550 | E14: -600 | F14: -580 | G14: =-G4*Assumptions!B11 | H14: =-H4*Assumptions!C11 | I14: =-I4*Assumptions!D11 | J14: =-J4*Assumptions!E11 | K14: =-K4*Assumptions!F11
A15: Unlevered Free Cash Flow (UFCF) | B15: =B10+B12+B13+B14 | C15: =C10+C12+C13+C14 | D15: =D10+D12+D13+D14 | E15: =E10+E12+E13+E14 | F15: =F10+F12+F13+F14 | G15: =G10+G12+G13+G14 | H15: =H10+H12+H13+H14 | I15: =I10+I12+I13+I14 | ... K15: =K10+K12+K13+K14

Sheet DCF Valuation
A1: DCF VALUATION — UNILEVER PLC (ULVR.L)
A2: Item | B2: 2025 | C2: 2026 | D2: 2027 | E2: 2028 | F2: 2029
A3: DISCOUNTED CASH FLOWS
A4: UFCF (£mm) | B4: ='Income Statement & FCF'!G15 | C4: ='Income Statement & FCF'!H15 | D4: ='Income Statement & FCF'!I15 | E4: ='Income Statement & FCF'!J15 | F4: ='Income Statement & FCF'!K15
A5: Discount Period | B5: 1 | C5: 2 | D5: 3 | E5: 4 | F5: 5
A6: Discount Factor | B6: =1/(1+Assumptions!B23)^B5 | C6: =1/(1+Assumptions!B23)^C5 | D6: =1/(1+Assumptions!B23)^D5 | E6: =1/(1+Assumptions!B23)^E5 | F6: =1/(1+Assumptions!B23)^F5
A7: PV of UFCF (£mm) | B7: =B4*B6 | C7: =C4*C6 | D7: =D4*D6 | E7: =E4*E6 | F7: =F4*F6
A9: TERMINAL VALUE
A10: Terminal Year UFCF (£mm) | B10: =F4
A11: Terminal Growth Rate | B11: =Assumptions!B26
A12: WACC | B12: =Assumptions!B23
A13: Terminal Value — Gordon Growth (£mm) | B13: =B10*(1+B11)/(B12-B11)
A14: PV of Terminal Value (£mm) | B14: =B13/(1+B12)^5
A15: Terminal Value as % of EV | B15: =B14/(SUM(B7:F7)+B14)
A17: ENTERPRISE & EQUITY VALUE
A18: Sum of PV of FCFs (£mm) | B18: =SUM(B7:F7)
A19: PV of Terminal Value (£mm) | B19: =B14
A20: Enterprise Value (£mm) | B20: =B18+B19
A21: Less: Net Debt (£mm) | B21: =-Assumptions!B30
A22: Equity Value (£mm) | B22: =B20+B21
A23: Shares Outstanding (mm) | B23: =Assumptions!B29
A24: Implied Share Price (£) | B24: =B22/B23
A25: Current Share Price (£) | B25: =Assumptions!B31
A26: Upside / (Downside) (%) | B26: =B24/B25-1

Sheet Sensitivity Analysis
A1: SENSITIVITY ANALYSIS — IMPLIED SHARE PRICE (£)
A3: Table 1: Share Price Sensitivity — WACC vs Terminal Growth Rate
A4: WACC \ TGR | B4: 1.5% | C4: 2.0% | D4: 2.5% | E4: 3.0% | F4: 3.5%
A5: 7.0% | B5: 46.5 | C5: 47.25 | D5: 48 | E5: 48.75 | F5: 49.5
A6: 7.5% | B6: 45.5 | C6: 46.25 | D6: 47 | E6: 47.75 | F6: 48.5
A7: 8.0% | B7: 44.5 | C7: 45.25 | D7: 46 | E7: 46.75 | F7: 47.5
A8: 8.5% | B8: 43.5 | C8: 44.25 | D8: 45 | E8: 45.75 | F8: 46.5
A9: 9.0% | B9: 42.5 | C9: 43.25 | D9: 44 | E9: 44.75 | F9: 45.5
A10: 9.5% | B10: 41.5 | C10: 42.25 | D10: 43 | E10: 43.75 | F10: 44.5
A11: 10.0% | B11: 40.5 | C11: 41.25 | D11: 42 | E11: 42.75 | F11: 43.5
A13: Note: Green = implied price above current market price (£38.50). Red = below market. Sensitivity illustrates directional impact of WACC and terminal growth rate assumptions on valuation.
