Workbook

Sheet Cover
B2: DISCOUNTED CASH FLOW MODEL
B4: UNILEVER PLC (ULVR.L · LSE)
B7: Analyst: | D7: Roman Falla
B8: Degree: | D8: BSc Economics & Management, University of Bristol
B9: Date: | D9: May 2026
B10: Model Version: | D10: 1.0
B11: Currency: | D11: GBP (£mm unless stated)
B12: Projection Period: | D12: FY2025E – FY2029E (5-year)
B13: Valuation Method: | D13: Unlevered DCF + Gordon Growth Terminal Value
B14: Cross-check: | D14: EV/EBITDA Exit Multiple
B17: DISCLAIMER: This model is built for educational and portfolio purposes only. It does not constitute investment advice. All figures are based on publicly available information and analyst estimates.

Sheet Assumptions
A1: UNILEVER PLC (ULVR.L) — DCF VALUATION MODEL
A2: Roman Falla · BSc Economics & Management, University of Bristol · May 2026
A4: KEY ASSUMPTIONS
A5: Assumption | B5: 2025 | C5: 2026 | D5: 2027 | E5: 2028 | F5: 2029
A6: Revenue Growth Rate (%) | B6: 0.04 | C6: 0.045 | D6: 0.048 | E6: 0.05 | F6: 0.05
A7: EBIT Margin (%) | B7: 0.16 | C7: 0.162 | D7: 0.165 | E7: 0.167 | F7: 0.17
A8: Tax Rate (%) | B8: 0.25 | C8: 0.25 | D8: 0.25 | E8: 0.25 | F8: 0.25
A9: D&A as % of Revenue (%) | B9: 0.04 | C9: 0.04 | D9: 0.039 | E9: 0.039 | F9: 0.038
A10: Capex as % of Revenue (%) | B10: 0.035 | C10: 0.035 | D10: 0.034 | E10: 0.034 | F10: 0.033
A11: Change in NWC as % Rev (%) | B11: 0.01 | C11: 0.01 | D11: 0.01 | E11: 0.01 | F11: 0.01
A13: WACC ASSUMPTIONS
A14: Risk-Free Rate (%) | B14: 0.045 | C14: Source: UK 10Y Gilt yield, May 2026
A15: Equity Risk Premium (%) | B15: 0.05 | C15: Source: Damodaran, Jan 2026
A16: Beta | B16: 0.65 | C16: Source: Bloomberg Terminal, 5Y monthly
A17: Cost of Equity (%) | B17: =B14+B16*B15 -> 0.0775 | C17: Ke = Rf + Beta x ERP
A18: Cost of Debt (pre-tax) (%) | B18: 0.04 | C18: Source: Unilever FY2024 Annual Report
A19: Tax Rate (%) | B19: 0.25 | C19: Consistent with income statement
A20: Cost of Debt (post-tax) (%) | B20: =B18*(1-B19) -> 0.03 | C20: Kd x (1 - Tax Rate)
A21: Debt / (Debt + Equity) | B21: 0.3 | C21: Source: Unilever FY2024 Balance Sheet
A22: Equity / (Debt + Equity) | B22: =1-B21 -> 0.7 | C22: 1 - D/(D+E)
A23: WACC (%) | B23: =B17*B22+B20*B21 -> 0.06325 | C23: Ke x E/V + Kd(1-t) x D/V
A25: TERMINAL VALUE ASSUMPTIONS
A26: Terminal Growth Rate (%) | B26: 0.025 | C26: Gordon Growth Model; below long-run UK nominal GDP
A27: Exit EV/EBITDA Multiple (cross-check) | B27: 12
A29: SHARE & BALANCE SHEET DATA
A30: Shares Outstanding (mm) | B30: 2587 | C30: Source: Unilever FY2024 Annual Report
A31: Net Debt (£mm) | B31: 9800 | C31: Source: Unilever FY2024 Balance Sheet
A32: Current Share Price (£) | B32: 38.5 | C32: Source: LSE, May 2026

Sheet Income Statement & FCF
A1: INCOME STATEMENT & FREE CASH FLOW BRIDGE (£mm)
A2: (£mm) | B2: 2020 | C2: 2021 | D2: 2022 | E2: 2023 | F2: 2024 | G2: 2025 | H2: 2026 | I2: 2027 | J2: 2028 | K2: 2029
A3: REVENUE
A4: Revenue | B4: 52444 | C4: 51980 | D4: 60073 | E4: 59955 | F4: 59949 | G4: =F4*(1+Assumptions!B6) -> 62346.96 | H4: =G4*(1+Assumptions!C6) -> 65152.573 | I4: =H4*(1+Assumptions!D6) -> 68279.897 | J4: =I4*(1+Assumptions!E6) -> 71693.892 | K4: =J4*(1+Assumptions!F6) -> 75278.586
A5: Revenue Growth (%) | B5: - | C5: =(C4-B4)/B4 -> -0.0088475326 | D5: =(D4-C4)/C4 -> 0.1556945 | E5: =(E4-D4)/D4 -> -0.0019642768 | F5: =(F4-E4)/E4 -> -0.00010007506 | G5: =(G4-F4)/F4 -> 0.04 | H5: =(H4-G4)/G4 -> 0.045 | I5: =(I4-H4)/H4 -> 0.048 | J5: =(J4-I4)/I4 -> 0.05 | K5: =(K4-J4)/J4 -> 0.05
A6: PROFITABILITY
A7: EBIT | B7: 8474 | C7: 8244 | D7: 9746 | E7: 9356 | F7: 9577 | G7: =G4*Assumptions!B7 -> 9975.5136 | H7: =H4*Assumptions!C7 -> 10554.717 | I7: =I4*Assumptions!D7 -> 11266.183 | J7: =J4*Assumptions!E7 -> 11972.88 | K7: =K4*Assumptions!F7 -> 12797.36
A8: EBIT Margin (%) | B8: =B7/B4 -> 0.16158188 | C8: =C7/C4 -> 0.15859946 | D8: =D7/D4 -> 0.16223595 | E8: =E7/E4 -> 0.15605037 | F8: =F7/F4 -> 0.15975246 | G8: =G7/G4 -> 0.16 | H8: =H7/H4 -> 0.162 | I8: =I7/I4 -> 0.165 | ... K8: =K7/K4 -> 0.17
A9: Tax | B9: =B7*0.25 -> 2118.5 | C9: =C7*0.25 -> 2061 | D9: =D7*0.25 -> 2436.5 | E9: =E7*0.25 -> 2339 | F9: =F7*0.25 -> 2394.25 | G9: =G7*Assumptions!B8 -> 2493.8784 | H9: =H7*Assumptions!C8 -> 2638.6792 | I9: =I7*Assumptions!D8 -> 2816.5457 | J9: =J7*Assumptions!E8 -> 2993.22 | K9: =K7*Assumptions!F8 -> 3199.3399
A10: NOPAT (EBIT after tax) | B10: =B7-B9 -> 6355.5 | C10: =C7-C9 -> 6183 | D10: =D7-D9 -> 7309.5 | E10: =E7-E9 -> 7017 | F10: =F7-F9 -> 7182.75 | G10: =G7-G9 -> 7481.6352 | H10: =H7-H9 -> 7916.0376 | I10: =I7-I9 -> 8449.6372 | ... K10: =K7-K9 -> 9598.0197
A11: FREE CASH FLOW BRIDGE
A12: D&A | B12: 1900 | C12: 1950 | D12: 2100 | E12: 2150 | F12: 2180 | G12: =G4*Assumptions!B9 -> 2493.8784 | H12: =H4*Assumptions!C9 -> 2606.1029 | I12: =I4*Assumptions!D9 -> 2662.916 | J12: =J4*Assumptions!E9 -> 2796.0618 | K12: =K4*Assumptions!F9 -> 2860.5863
A13: Capex | B13: -1700 | C13: -1650 | D13: -2000 | E13: -2050 | F13: -2100 | G13: =-G4*Assumptions!B10 -> -2182.1436 | H13: =-H4*Assumptions!C10 -> -2280.3401 | I13: =-I4*Assumptions!D10 -> -2321.5165 | J13: =-J4*Assumptions!E10 -> -2437.5923 | K13: =-K4*Assumptions!F10 -> -2484.1933
A14: Change in NWC | B14: -500 | C14: -400 | D14: -550 | E14: -600 | F14: -580 | G14: =-G4*Assumptions!B11 -> -623.4696 | H14: =-H4*Assumptions!C11 -> -651.52573 | I14: =-I4*Assumptions!D11 -> -682.79897 | J14: =-J4*Assumptions!E11 -> -716.93892 | K14: =-K4*Assumptions!F11 -> -752.78586
A15: Unlevered Free Cash Flow (UFCF) | B15: =B10+B12+B13+B14 -> 6055.5 | C15: =C10+C12+C13+C14 -> 6083 | D15: =D10+D12+D13+D14 -> 6859.5 | E15: =E10+E12+E13+E14 -> 6517 | F15: =F10+F12+F13+F14 -> 6682.75 | G15: =G10+G12+G13+G14 -> 7169.9004 | H15: =H10+H12+H13+H14 -> 7590.2748 | I15: =I10+I12+I13+I14 -> 8108.2377 | ... K15: =K10+K12+K13+K14 -> 9221.6268

Sheet DCF Valuation
A1: DCF VALUATION — UNILEVER PLC (ULVR.L)
A2: Item | B2: 2025 | C2: 2026 | D2: 2027 | E2: 2028 | F2: 2029
A3: DISCOUNTED CASH FLOWS
A4: UFCF (£mm) | B4: ='Income Statement & FCF'!G15 -> 7169.9004 | C4: ='Income Statement & FCF'!H15 -> 7590.2748 | D4: ='Income Statement & FCF'!I15 -> 8108.2377 | E4: ='Income Statement & FCF'!J15 -> 8621.1905 | F4: ='Income Statement & FCF'!K15 -> 9221.6268
A5: Discount Period | B5: 1 | C5: 2 | D5: 3 | E5: 4 | F5: 5
A6: Discount Factor | B6: =1/(1+Assumptions!B23)^B5 -> 0.94051258 | C6: =1/(1+Assumptions!B23)^C5 -> 0.88456391 | D6: =1/(1+Assumptions!B23)^D5 -> 0.83194349 | E6: =1/(1+Assumptions!B23)^E5 -> 0.78245331 | F6: =1/(1+Assumptions!B23)^F5 -> 0.73590718
A7: PV of UFCF (£mm) | B7: =B4*B6 -> 6743.3815 | C7: =C4*C6 -> 6714.0832 | D7: =D4*D6 -> 6745.5956 | E7: =E4*E6 -> 6745.679 | F7: =F4*F6 -> 6786.2614
A9: TERMINAL VALUE
A10: Terminal Year UFCF (£mm) | B10: =F4 -> 9221.6268
A11: Terminal Growth Rate | B11: =Assumptions!B26 -> 0.025
A12: WACC | B12: =Assumptions!B23 -> 0.06325
A13: Terminal Value — Gordon Growth (£mm) | B13: =B10*(1+B11)/(B12-B11) -> 247115.49
A14: PV of Terminal Value (£mm) | B14: =B13/(1+B12)^5 -> 181854.06
A15: Terminal Value as % of EV | B15: =B14/(SUM(B7:F7)+B14) -> 0.84352174
A17: ENTERPRISE & EQUITY VALUE
A18: Sum of PV of FCFs (£mm) | B18: =SUM(B7:F7) -> 33735.001
A19: PV of Terminal Value (£mm) | B19: =B14 -> 181854.06
A20: Enterprise Value (£mm) | B20: =B18+B19 -> 215589.06
A21: Less: Net Debt (£mm) | B21: =-Assumptions!B31 -> -9800
A22: Equity Value (£mm) | B22: =B20+B21 -> 205789.06
A23: Shares Outstanding (mm) | B23: =Assumptions!B30 -> 2587
A24: Implied Share Price (£) | B24: =B22/B23 -> 79.547377
A25: Current Share Price (£) | B25: =Assumptions!B32 -> 38.5
A26: Upside / (Downside) (%) | B26: =B24/B25-1 -> 1.0661656

Sheet Sensitivity Analysis
A1: SENSITIVITY ANALYSIS — IMPLIED SHARE PRICE (£)
A3: Table 1: Share Price Sensitivity — WACC vs Terminal Growth Rate
A4: WACC \ TGR | B4: =Assumptions!$B$26+(0-2)*0.005 -> 0.015 | C4: =Assumptions!$B$26+(1-2)*0.005 -> 0.02 | D4: =Assumptions!$B$26+(2-2)*0.005 -> 0.025 | E4: =Assumptions!$B$26+(3-2)*0.005 -> 0.03 | F4: =Assumptions!$B$26+(4-2)*0.005 -> 0.035
A5: =Assumptions!$B$23+(0-3)*0.005 -> 0.04825 | B5: =(SUMPRODUCT('DCF Valuation'!$B$4:$F$4/(1+$A5)^'DCF Valuation'!$B$5:$F$5)+'DCF Valuation'!$F$4*(1+B$4)/($A5-B$4)/(1+$A5)^5-Assumptions!$B$31)/Assumptions!$B$30 -> 95.796117 | C5: =(SUMPRODUCT('DCF Valuation'!$B$4:$F$4/(1+$A5)^'DCF Valuation'!$B$5:$F$5)+'DCF Valuation'!$F$4*(1+C$4)/($A5-C$4)/(1+$A5)^5-Assumptions!$B$31)/Assumptions!$B$30 -> 111.51101 | D5: =(SUMPRODUCT('DCF Valuation'!$B$4:$F$4/(1+$A5)^'DCF Valuation'!$B$5:$F$5)+'DCF Valuation'!$F$4*(1+D$4)/($A5-D$4)/(1+$A5)^5-Assumptions!$B$31)/Assumptions!$B$30 -> 133.98501 | E5: =(SUMPRODUCT('DCF Valuation'!$B$4:$F$4/(1+$A5)^'DCF Valuation'!$B$5:$F$5)+'DCF Valuation'!$F$4*(1+E$4)/($A5-E$4)/(1+$A5)^5-Assumptions!$B$31)/Assumptions!$B$30 -> 168.77351 | F5: =(SUMPRODUCT('DCF Valuation'!$B$4:$F$4/(1+$A5)^'DCF Valuation'!$B$5:$F$5)+'DCF Valuation'!$F$4*(1+F$4)/($A5-F$4)/(1+$A5)^5-Assumptions!$B$31)/Assumptions!$B$30 -> 229.8175
A6: =Assumptions!$B$23+(1-3)*0.005 -> 0.05325 | B6: =(SUMPRODUCT('DCF Valuation'!$B$4:$F$4/(1+$A6)^'DCF Valuation'!$B$5:$F$5)+'DCF Valuation'!$F$4*(1+B$4)/($A6-B$4)/(1+$A6)^5-Assumptions!$B$31)/Assumptions!$B$30 -> 82.606034 | C6: =(SUMPRODUCT('DCF Valuation'!$B$4:$F$4/(1+$A6)^'DCF Valuation'!$B$5:$F$5)+'DCF Valuation'!$F$4*(1+C$4)/($A6-C$4)/(1+$A6)^5-Assumptions!$B$31)/Assumptions!$B$30 -> 93.993633 | D6: =(SUMPRODUCT('DCF Valuation'!$B$4:$F$4/(1+$A6)^'DCF Valuation'!$B$5:$F$5)+'DCF Valuation'!$F$4*(1+D$4)/($A6-D$4)/(1+$A6)^5-Assumptions!$B$31)/Assumptions!$B$30 -> 109.41224 | E6: =(SUMPRODUCT('DCF Valuation'!$B$4:$F$4/(1+$A6)^'DCF Valuation'!$B$5:$F$5)+'DCF Valuation'!$F$4*(1+E$4)/($A6-E$4)/(1+$A6)^5-Assumptions!$B$31)/Assumptions!$B$30 -> 131.46251 | F6: =(SUMPRODUCT('DCF Valuation'!$B$4:$F$4/(1+$A6)^'DCF Valuation'!$B$5:$F$5)+'DCF Valuation'!$F$4*(1+F$4)/($A6-F$4)/(1+$A6)^5-Assumptions!$B$31)/Assumptions!$B$30 -> 165.59511
A7: =Assumptions!$B$23+(2-3)*0.005 -> 0.05825 | B7: =(SUMPRODUCT('DCF Valuation'!$B$4:$F$4/(1+$A7)^'DCF Valuation'!$B$5:$F$5)+'DCF Valuation'!$F$4*(1+B$4)/($A7-B$4)/(1+$A7)^5-Assumptions!$B$31)/Assumptions!$B$30 -> 72.468593 | C7: =(SUMPRODUCT('DCF Valuation'!$B$4:$F$4/(1+$A7)^'DCF Valuation'!$B$5:$F$5)+'DCF Valuation'!$F$4*(1+C$4)/($A7-C$4)/(1+$A7)^5-Assumptions!$B$31)/Assumptions!$B$30 -> 81.058935 | D7: =(SUMPRODUCT('DCF Valuation'!$B$4:$F$4/(1+$A7)^'DCF Valuation'!$B$5:$F$5)+'DCF Valuation'!$F$4*(1+D$4)/($A7-D$4)/(1+$A7)^5-Assumptions!$B$31)/Assumptions!$B$30 -> 92.232839 | E7: =(SUMPRODUCT('DCF Valuation'!$B$4:$F$4/(1+$A7)^'DCF Valuation'!$B$5:$F$5)+'DCF Valuation'!$F$4*(1+E$4)/($A7-E$4)/(1+$A7)^5-Assumptions!$B$31)/Assumptions!$B$30 -> 107.36211 | F7: =(SUMPRODUCT('DCF Valuation'!$B$4:$F$4/(1+$A7)^'DCF Valuation'!$B$5:$F$5)+'DCF Valuation'!$F$4*(1+F$4)/($A7-F$4)/(1+$A7)^5-Assumptions!$B$31)/Assumptions!$B$30 -> 128.99859
A8: =Assumptions!$B$23+(3-3)*0.005 -> 0.06325 | B8: =(SUMPRODUCT('DCF Valuation'!$B$4:$F$4/(1+$A8)^'DCF Valuation'!$B$5:$F$5)+'DCF Valuation'!$F$4*(1+B$4)/($A8-B$4)/(1+$A8)^5-Assumptions!$B$31)/Assumptions!$B$30 -> 64.434721 | C8: =(SUMPRODUCT('DCF Valuation'!$B$4:$F$4/(1+$A8)^'DCF Valuation'!$B$5:$F$5)+'DCF Valuation'!$F$4*(1+C$4)/($A8-C$4)/(1+$A8)^5-Assumptions!$B$31)/Assumptions!$B$30 -> 71.117485 | D8: =(SUMPRODUCT('DCF Valuation'!$B$4:$F$4/(1+$A8)^'DCF Valuation'!$B$5:$F$5)+'DCF Valuation'!$F$4*(1+D$4)/($A8-D$4)/(1+$A8)^5-Assumptions!$B$31)/Assumptions!$B$30 -> 79.547377 | E8: =(SUMPRODUCT('DCF Valuation'!$B$4:$F$4/(1+$A8)^'DCF Valuation'!$B$5:$F$5)+'DCF Valuation'!$F$4*(1+E$4)/($A8-E$4)/(1+$A8)^5-Assumptions!$B$31)/Assumptions!$B$30 -> 90.512575 | F8: =(SUMPRODUCT('DCF Valuation'!$B$4:$F$4/(1+$A8)^'DCF Valuation'!$B$5:$F$5)+'DCF Valuation'!$F$4*(1+F$4)/($A8-F$4)/(1+$A8)^5-Assumptions!$B$31)/Assumptions!$B$30 -> 105.35926
A9: =Assumptions!$B$23+(4-3)*0.005 -> 0.06825 | B9: =(SUMPRODUCT('DCF Valuation'!$B$4:$F$4/(1+$A9)^'DCF Valuation'!$B$5:$F$5)+'DCF Valuation'!$F$4*(1+B$4)/($A9-B$4)/(1+$A9)^5-Assumptions!$B$31)/Assumptions!$B$30 -> 57.911808 | C9: =(SUMPRODUCT('DCF Valuation'!$B$4:$F$4/(1+$A9)^'DCF Valuation'!$B$5:$F$5)+'DCF Valuation'!$F$4*(1+C$4)/($A9-C$4)/(1+$A9)^5-Assumptions!$B$31)/Assumptions!$B$30 -> 63.238684 | D9: =(SUMPRODUCT('DCF Valuation'!$B$4:$F$4/(1+$A9)^'DCF Valuation'!$B$5:$F$5)+'DCF Valuation'!$F$4*(1+D$4)/($A9-D$4)/(1+$A9)^5-Assumptions!$B$31)/Assumptions!$B$30 -> 69.797207 | E9: =(SUMPRODUCT('DCF Valuation'!$B$4:$F$4/(1+$A9)^'DCF Valuation'!$B$5:$F$5)+'DCF Valuation'!$F$4*(1+E$4)/($A9-E$4)/(1+$A9)^5-Assumptions!$B$31)/Assumptions!$B$30 -> 78.070377 | F9: =(SUMPRODUCT('DCF Valuation'!$B$4:$F$4/(1+$A9)^'DCF Valuation'!$B$5:$F$5)+'DCF Valuation'!$F$4*(1+F$4)/($A9-F$4)/(1+$A9)^5-Assumptions!$B$31)/Assumptions!$B$30 -> 88.831719
A10: =Assumptions!$B$23+(5-3)*0.005 -> 0.07325 | B10: =(SUMPRODUCT('DCF Valuation'!$B$4:$F$4/(1+$A10)^'DCF Valuation'!$B$5:$F$5)+'DCF Valuation'!$F$4*(1+B$4)/($A10-B$4)/(1+$A10)^5-Assumptions!$B$31)/Assumptions!$B$30 -> 52.510713 | C10: =(SUMPRODUCT('DCF Valuation'!$B$4:$F$4/(1+$A10)^'DCF Valuation'!$B$5:$F$5)+'DCF Valuation'!$F$4*(1+C$4)/($A10-C$4)/(1+$A10)^5-Assumptions!$B$31)/Assumptions!$B$30 -> 56.841452 | D10: =(SUMPRODUCT('DCF Valuation'!$B$4:$F$4/(1+$A10)^'DCF Valuation'!$B$5:$F$5)+'DCF Valuation'!$F$4*(1+D$4)/($A10-D$4)/(1+$A10)^5-Assumptions!$B$31)/Assumptions!$B$30 -> 62.069753 | E10: =(SUMPRODUCT('DCF Valuation'!$B$4:$F$4/(1+$A10)^'DCF Valuation'!$B$5:$F$5)+'DCF Valuation'!$F$4*(1+E$4)/($A10-E$4)/(1+$A10)^5-Assumptions!$B$31)/Assumptions!$B$30 -> 68.50691 | F10: =(SUMPRODUCT('DCF Valuation'!$B$4:$F$4/(1+$A10)^'DCF Valuation'!$B$5:$F$5)+'DCF Valuation'!$F$4*(1+F$4)/($A10-F$4)/(1+$A10)^5-Assumptions!$B$31)/Assumptions!$B$30 -> 76.626984
A11: =Assumptions!$B$23+(6-3)*0.005 -> 0.07825 | B11: =(SUMPRODUCT('DCF Valuation'!$B$4:$F$4/(1+$A11)^'DCF Valuation'!$B$5:$F$5)+'DCF Valuation'!$F$4*(1+B$4)/($A11-B$4)/(1+$A11)^5-Assumptions!$B$31)/Assumptions!$B$30 -> 47.96535 | C11: =(SUMPRODUCT('DCF Valuation'!$B$4:$F$4/(1+$A11)^'DCF Valuation'!$B$5:$F$5)+'DCF Valuation'!$F$4*(1+C$4)/($A11-C$4)/(1+$A11)^5-Assumptions!$B$31)/Assumptions!$B$30 -> 51.544227 | D11: =(SUMPRODUCT('DCF Valuation'!$B$4:$F$4/(1+$A11)^'DCF Valuation'!$B$5:$F$5)+'DCF Valuation'!$F$4*(1+D$4)/($A11-D$4)/(1+$A11)^5-Assumptions!$B$31)/Assumptions!$B$30 -> 55.795194 | E11: =(SUMPRODUCT('DCF Valuation'!$B$4:$F$4/(1+$A11)^'DCF Valuation'!$B$5:$F$5)+'DCF Valuation'!$F$4*(1+E$4)/($A11-E$4)/(1+$A11)^5-Assumptions!$B$31)/Assumptions!$B$30 -> 60.92719 | F11: =(SUMPRODUCT('DCF Valuation'!$B$4:$F$4/(1+$A11)^'DCF Valuation'!$B$5:$F$5)+'DCF Valuation'!$F$4*(1+F$4)/($A11-F$4)/(1+$A11)^5-Assumptions!$B$31)/Assumptions!$B$30 -> 67.245774
A13: Note: Green = implied price above current market price (Assumptions B32). Red = at or below market. Centre row and column are the model WACC and terminal growth rate, so the middle cell equals the DCF Valuation implied share price.
