Workbook

Sheet Cover
B2: DISCOUNTED CASH FLOW MODEL
B4: UNILEVER PLC (ULVR.L · LSE)
B7: Analyst: | D7: Roman Falla
B8: Degree: | D8: BSc Economics & Management, University of Bristol
B9: Date: | D9: October 2026
B10: Model Version: | D10: 2.0 — FY2025A rebased
B11: Currency: | D11: GBP (£mm unless stated)
B12: Projection Period: | D12: FY2026E – FY2030E (5-year)
B13: Valuation Method: | D13: Unlevered DCF + Gordon Growth Terminal Value
B14: Cross-check: | D14: EV/EBITDA Exit Multiple
B16: FY2025 actuals are continuing operations excluding Ice Cream. Euro reported figures are converted to GBP using Unilever's published FY2025 average EUR/GBP rate for P&L/cash-flow items. Balance-sheet items use a separate year-end FX assumption.

Sheet Assumptions
A1: UNILEVER PLC (ULVR.L) — DCF VALUATION MODEL
A2: Roman Falla · BSc Economics & Management, University of Bristol · October 2026
A4: OPERATING ASSUMPTIONS
A5: Assumption | B5: 2026E | C5: 2027E | D5: 2028E | E5: 2029E | F5: 2030E | G5: Basis
A6: Revenue Growth (%) | B6: 0.045 | C6: 0.048 | D6: 0.05 | E6: 0.05 | F6: 0.05 | G6: Author assumption; 2026 sits within Unilever's 4–6% underlying sales-growth guidance range, with reported GBP growth affected by FX/disposals.
A7: EBIT Margin (%) | B7: 0.179 | C7: 0.181 | D7: 0.183 | E7: 0.185 | F7: 0.187 | G7: FY2025A reported EBIT margin = 17.9%; gradual expansion is an author forecast, not company guidance.
A8: Tax Rate (%) | B8: 0.257 | C8: 0.257 | D8: 0.257 | E8: 0.257 | F8: 0.257 | G8: FY2025 underlying effective tax rate = 25.7%.
A9: D&A as % Revenue | B9: 0.026 | C9: 0.026 | D9: 0.026 | E9: 0.026 | F9: 0.026 | G9: FY2025A D&A €1,310m / turnover €50,503m ≈ 2.6%.
A10: Capex as % Revenue | B10: 0.031503079 | C10: 0.031503079 | D10: 0.031503079 | E10: 0.031503079 | F10: 0.031503079 | G10: FY2025A gross capex €1,591m / turnover €50,503m ≈ 3.15%.
A11: Change in NWC as % Revenue | B11: 0.003 | C11: 0.003 | D11: 0.003 | E11: 0.003 | F11: 0.003 | G11: Normalised assumption. FY2025 reported working-capital cash inflow was €116m, so a 0.3% revenue inflow is deliberately conservative.
A13: WACC ASSUMPTIONS
A14: Risk-Free Rate (%) | B14: 0.045 | C14: User-selected modelling input; refresh with the relevant UK 10Y gilt yield.
A15: Equity Risk Premium (%) | B15: 0.05 | C15: User-selected modelling input.
A16: Beta | B16: 0.65 | C16: User-selected modelling input.
A17: Cost of Equity (%) | B17: =B14+B16*B15 -> 0.0775 | C17: CAPM = Rf + Beta × ERP.
A18: Pre-tax Cost of Debt (%) | B18: 0.04 | C18: User-selected modelling input.
A19: Post-tax Cost of Debt (%) | B19: =B18*(1-B8) -> 0.02972 | C19: Kd × (1 − tax rate).
A20: Debt / (Debt + Equity) | B20: =B23/(B22+B23) -> 0.16598645 | C20: Market-value capital structure weight.
A21: Equity / (Debt + Equity) | B21: =1-B20 -> 0.83401355 | C21: 1 − debt weight.
A22: Market Capitalisation (£mm) | B22: =B36*B35 -> 100758.29 | C22: Current share price × FY2025 year-end share count.
A23: Net Debt (£mm) | B23: ='FY25 Actuals EUR'!C13*'FY25 Actuals EUR'!B20 -> 20053.044 | C23: FY2025 closing net debt × year-end FX.
A24: Calculated WACC (%) | B24: =B17*B21+B19*B20 -> 0.069569167 | C24: Calculated market-based WACC.
A25: DCF WACC used (%) | B25: 0.082 | C25: User-selected 8.2% WACC retained as the main DCF scenario.
A27: TERMINAL VALUE / EQUITY BRIDGE
A28: Terminal Growth Rate (%) | B28: 0.025 | C28: Gordon Growth assumption; must remain below WACC.
A29: Exit EV/EBITDA Multiple | B29: 12 | C29: Cross-check assumption applied to FY2030E EBITDA.
A30: NCI Valuation Multiple | B30: 0 | C30: Not used in the main bridge; NCI is deducted at FY2025 book value.
A31: NCI (£mm) | B31: ='FY25 Actuals EUR'!C14*'FY25 Actuals EUR'!B20 -> 1787.533 | C31: FY2025 balance-sheet NCI converted at year-end FX.
A32: Retained TMICC stake (£mm) | B32: ='FY25 Actuals EUR'!C15*'FY25 Actuals EUR'!B20 -> 1438.195 | C32: Retained 19.85% stake, treated as a non-operating asset.
A34: SHARE DATA
A35: Shares Outstanding (mm) | B35: ='FY25 Actuals EUR'!C16 -> 2179.5
A36: Current Share Price (£) | B36: 46.23 | C36: Market reference price; the DCF balance sheet remains FY2025A.
A37: FX: £ per €1 — average | B37: ='FY25 Actuals EUR'!B19 -> 0.855
A38: FX: £ per €1 — year-end | B38: ='FY25 Actuals EUR'!B20 -> 0.869

Sheet FY25 Actuals EUR
A1: FY2025 ACTUALS — UNILEVER CONTINUING OPERATIONS (€mm)
A2: Item | B2: FY2024A | C2: FY2025A | D2: Source / note
A4: Turnover | B4: 52479 | C4: 50503 | D4: Source: Unilever Annual Report and Accounts 2025, continuing operations; 2024 comparatives re-presented for Ice Cream demerger.
A5: Operating profit (EBIT) | B5: 8829 | C5: 9037 | D5: Operating profit is the reported EBIT line used as the DCF starting point.
A6: Underlying operating profit | B6: 10198 | C6: 10084
A7: Depreciation & amortisation | B7: 1236 | C7: 1310 | D7: Depreciation and amortisation used in Unilever's EBITDA reconciliation.
A8: Purchase of PP&E | B8: 1381 | C8: 1417
A9: Purchase of intangible assets | B9: 233 | C9: 174
A10: Total gross capex | B10: =C8+C9 -> 1591 | C10: =C8+C9 -> 1591 | D10: Gross capex = PP&E purchases + intangible purchases.
A11: Change in working capital | B11: -188 | C11: 116 | D11: Positive value is a cash inflow / working-capital release.
A12: Underlying effective tax rate | B12: 0.259 | C12: 0.257 | D12: Underlying effective tax rate. DCF uses this as a normalised tax assumption.
A13: Net debt | B13: 24519 | C13: 23076 | D13: Closing net debt at 31 Dec 2025.
A14: Non-controlling interests | B14: 2565 | C14: 2057
A15: Retained TMICC equity investment | C15: 1655 | D15: Fair value of Unilever's retained 19.85% TMICC stake at the demerger.
A16: Shares outstanding, net of treasury (mm) | C16: 2179.5 | D16: Shares at 31 Dec 2025 after the 8-for-9 share consolidation, net of treasury shares.
A18: FX ASSUMPTIONS
A19: FY2025 average £ per €1 | B19: 0.855 | D19: Use published average rate for income statement and cash-flow items.
A20: Year-end £ per €1 | B20: 0.869 | D20: Used for net debt, NCI and retained TMICC stake.

Sheet Income Statement & FCF
A1: INCOME STATEMENT & FREE CASH FLOW BRIDGE (£mm)
B2: 2025A | C2: 2026E | D2: 2027E | E2: 2028E | F2: 2029E | G2: 2030E
A3: REVENUE
A4: Revenue | B4: ='FY25 Actuals EUR'!C4*'FY25 Actuals EUR'!B19 -> 43180.065 | C4: =B4*(1+Assumptions!B6) -> 45123.168 | D4: =C4*(1+Assumptions!C6) -> 47289.08 | E4: =D4*(1+Assumptions!D6) -> 49653.534 | F4: =E4*(1+Assumptions!E6) -> 52136.211 | G4: =F4*(1+Assumptions!F6) -> 54743.021
A5: Revenue Growth (%) | B5: n/a | C5: =C4/B4-1 -> 0.045 | D5: =D4/C4-1 -> 0.048 | E5: =E4/D4-1 -> 0.05 | F5: =F4/E4-1 -> 0.05 | G5: =G4/F4-1 -> 0.05
A7: PROFITABILITY
A8: EBIT | B8: ='FY25 Actuals EUR'!C5*'FY25 Actuals EUR'!B19 -> 7726.635 | C8: =C4*Assumptions!B7 -> 8077.0471 | D8: =D4*Assumptions!C7 -> 8559.3235 | E8: =E4*Assumptions!D7 -> 9086.5967 | F8: =F4*Assumptions!E7 -> 9645.199 | G8: =G4*Assumptions!F7 -> 10236.945
A9: EBIT Margin (%) | B9: =B8/B4 -> 0.17893986 | C9: =C8/C4 -> 0.179 | D9: =D8/D4 -> 0.181 | E9: =E8/E4 -> 0.183 | F9: =F8/F4 -> 0.185 | G9: =G8/G4 -> 0.187
A10: Tax | B10: =-B8*'FY25 Actuals EUR'!C12 -> -1985.7452 | C10: =-C8*Assumptions!B8 -> -2075.8011 | D10: =-D8*Assumptions!C8 -> -2199.7461 | E10: =-E8*Assumptions!D8 -> -2335.2554 | F10: =-F8*Assumptions!E8 -> -2478.8161 | G10: =-G8*Assumptions!F8 -> -2630.8949
A11: NOPAT (EBIT after tax) | B11: =B8+B10 -> 5740.8898 | C11: =C8+C10 -> 6001.246 | D11: =D8+D10 -> 6359.5773 | E11: =E8+E10 -> 6751.3414 | F11: =F8+F10 -> 7166.3828 | G11: =G8+G10 -> 7606.0501
A13: FREE CASH FLOW BRIDGE
A14: D&A | B14: ='FY25 Actuals EUR'!C7*'FY25 Actuals EUR'!B19 -> 1120.05 | C14: =C4*Assumptions!B9 -> 1173.2024 | D14: =D4*Assumptions!C9 -> 1229.5161 | E14: =E4*Assumptions!D9 -> 1290.9919 | F14: =F4*Assumptions!E9 -> 1355.5415 | G14: =G4*Assumptions!F9 -> 1423.3186
A15: Capex | B15: =-'FY25 Actuals EUR'!C10*'FY25 Actuals EUR'!B19 -> -1360.305 | C15: =-C4*Assumptions!B10 -> -1421.5187 | D15: =-D4*Assumptions!C10 -> -1489.7516 | E15: =-E4*Assumptions!D10 -> -1564.2392 | F15: =-F4*Assumptions!E10 -> -1642.4512 | G15: =-G4*Assumptions!F10 -> -1724.5737
A16: Change in NWC | B16: ='FY25 Actuals EUR'!C11*'FY25 Actuals EUR'!B19 -> 99.18 | C16: =C4*Assumptions!B11 -> 135.3695 | D16: =D4*Assumptions!C11 -> 141.86724 | E16: =E4*Assumptions!D11 -> 148.9606 | F16: =F4*Assumptions!E11 -> 156.40863 | G16: =G4*Assumptions!F11 -> 164.22906
A17: Unlevered Free Cash Flow (UFCF) | B17: =B11+B14+B15+B16 -> 5599.8148 | C17: =C11+C14+C15+C16 -> 5888.2991 | D17: =D11+D14+D15+D16 -> 6241.209 | E17: =E11+E14+E15+E16 -> 6627.0546 | F17: =F11+F14+F15+F16 -> 7035.8818 | G17: =G11+G14+G15+G16 -> 7469.024
A18: Underlying EBITDA (memo) | B18: =B8+B14 -> 8846.685 | C18: =C8+C14 -> 9250.2494 | D18: =D8+D14 -> 9788.8396 | E18: =E8+E14 -> 10377.589 | F18: =F8+F14 -> 11000.74 | G18: =G8+G14 -> 11660.264
A20: Method note: reported operating profit (EBIT) is used rather than underlying operating profit, avoiding an automatic assumption that all non-underlying costs are non-cash or non-recurring. The forecast EBIT margin therefore starts from the reported 17.9% FY2025A margin and expands gradually.

Sheet DCF Valuation
A1: DCF VALUATION — UNILEVER PLC (ULVR.L)
B2: 2026E | C2: 2027E | D2: 2028E | E2: 2029E | F2: 2030E
A3: DISCOUNTED CASH FLOWS
A4: UFCF (£mm) | B4: ='Income Statement & FCF'!C17 -> 5888.2991 | C4: ='Income Statement & FCF'!D17 -> 6241.209 | D4: ='Income Statement & FCF'!E17 -> 6627.0546 | E4: ='Income Statement & FCF'!F17 -> 7035.8818 | F4: ='Income Statement & FCF'!G17 -> 7469.024
A5: Discount Period | B5: 1 | C5: 2 | D5: 3 | E5: 4 | F5: 5
A6: Discount Factor | B6: =1/(1+Assumptions!$B$25)^B5 -> 0.92421442 | C6: =1/(1+Assumptions!$B$25)^C5 -> 0.85417229 | D6: =1/(1+Assumptions!$B$25)^D5 -> 0.78943835 | E6: =1/(1+Assumptions!$B$25)^E5 -> 0.7296103 | F6: =1/(1+Assumptions!$B$25)^F5 -> 0.67431636
A7: PV of UFCF (£mm) | B7: =B4*B6 -> 5442.0509 | C7: =C4*C6 -> 5331.0678 | D7: =D4*D6 -> 5231.6511 | E7: =E4*E6 -> 5133.4518 | F7: =F4*F6 -> 5036.4851
A9: TERMINAL VALUE — GORDON GROWTH
A10: Terminal Year UFCF (£mm) | B10: =F4 -> 7469.024
A11: Terminal Growth Rate | B11: =Assumptions!B28 -> 0.025
A12: WACC | B12: =Assumptions!B25 -> 0.082
A13: Terminal Value — Gordon Growth (£mm) | B13: =B10*(1+B11)/(B12-B11) -> 134311.4
A14: PV of Terminal Value (£mm) | B14: =B13/(1+B12)^F5 -> 90568.372
A15: Terminal Value as % of EV | B15: =B14/B21 -> 0.77579222
A16: Implied Terminal EV/EBITDA | B16: =B13/'Income Statement & FCF'!G18 -> 11.518727
A18: ENTERPRISE & EQUITY VALUE — GORDON GROWTH
A19: Sum of PV of FCFs (£mm) | B19: =SUM(B7:F7) -> 26174.707
A20: PV of Terminal Value (£mm) | B20: =B14 -> 90568.372
A21: Enterprise Value (£mm) | B21: =B19+B20 -> 116743.08
A22: Less: Net Debt (£mm) | B22: =-Assumptions!B23 -> -20053.044
A23: Less: Non-controlling interests (£mm) | B23: =-Assumptions!B31 -> -1787.533
A24: Plus: Retained TMICC stake (£mm) | B24: =Assumptions!B32 -> 1438.195
A25: Equity Value (£mm) | B25: =SUM(B21:B24) -> 96340.697
A26: Shares Outstanding (mm) | B26: =Assumptions!B35 -> 2179.5
A27: Implied Share Price (£) | B27: =B25/B26 -> 44.203118 | G27: Main DCF uses the user-selected 8.2% WACC. The calculated market-based WACC is shown on Assumptions B24 for transparency.
A28: Current Share Price (£) | B28: =Assumptions!B36 -> 46.23
A29: Upside / (Downside) (%) | B29: =B27/B28-1 -> -0.043843425
A31: EXIT MULTIPLE CROSS-CHECK
A32: FY2030E Underlying EBITDA (£mm) | B32: ='Income Statement & FCF'!G18 -> 11660.264
A33: Exit EV/EBITDA Multiple | B33: =Assumptions!B29 -> 12
A34: Terminal Value — Exit Multiple (£mm) | B34: =B32*B33 -> 139923.16
A35: PV of Terminal Value (£mm) | B35: =B34/(1+B12)^F5 -> 94352.477
A36: Enterprise Value (£mm) | B36: =B19+B35 -> 120527.18
A37: Equity Value (£mm) | B37: =B36+B22+B23+B24 -> 100124.8
A38: Implied Share Price (£) | B38: =B37/B26 -> 45.939345
A39: Difference vs Gordon Growth (%) | B39: =B38/B27-1 -> 0.039278369 | G39: A large difference between terminal methods is not automatically an error; it is a signal to revisit the WACC, terminal growth rate, or exit multiple.
A40: Implied Perpetual Growth Rate (%) | B40: =(B34*B12-F4)/(B34+F4) -> 0.027170201
A41: Terminal Value as % of EV | B41: =B35/B36 -> 0.78283151

Sheet Sensitivity Analysis
A1: SENSITIVITY ANALYSIS — IMPLIED SHARE PRICE (£)
A3: TABLE 1: GORDON GROWTH — WACC VS TERMINAL GROWTH
A4: WACC \ TGR | B4: =Assumptions!$B$28+(0-2)*0.005 -> 0.015 | C4: =Assumptions!$B$28+(1-2)*0.005 -> 0.02 | D4: =Assumptions!$B$28+(2-2)*0.005 -> 0.025 | E4: =Assumptions!$B$28+(3-2)*0.005 -> 0.03 | F4: =Assumptions!$B$28+(4-2)*0.005 -> 0.035
A5: =Assumptions!$B$25+(0-3)*0.005 -> 0.067 | B5: =(SUMPRODUCT('DCF Valuation'!$B$4:$F$4/(1+$A5)^'DCF Valuation'!$B$5:$F$5)+'DCF Valuation'!$F$4*(1+B$4)/($A5-B$4)/(1+$A5)^'DCF Valuation'!$F$5-Assumptions!$B$23-Assumptions!$B$31+Assumptions!$B$32)/Assumptions!$B$35 -> 51.524638 | C5: =(SUMPRODUCT('DCF Valuation'!$B$4:$F$4/(1+$A5)^'DCF Valuation'!$B$5:$F$5)+'DCF Valuation'!$F$4*(1+C$4)/($A5-C$4)/(1+$A5)^'DCF Valuation'!$F$5-Assumptions!$B$23-Assumptions!$B$31+Assumptions!$B$32)/Assumptions!$B$35 -> 56.933652 | D5: =(SUMPRODUCT('DCF Valuation'!$B$4:$F$4/(1+$A5)^'DCF Valuation'!$B$5:$F$5)+'DCF Valuation'!$F$4*(1+D$4)/($A5-D$4)/(1+$A5)^'DCF Valuation'!$F$5-Assumptions!$B$23-Assumptions!$B$31+Assumptions!$B$32)/Assumptions!$B$35 -> 63.630527 | E5: =(SUMPRODUCT('DCF Valuation'!$B$4:$F$4/(1+$A5)^'DCF Valuation'!$B$5:$F$5)+'DCF Valuation'!$F$4*(1+E$4)/($A5-E$4)/(1+$A5)^'DCF Valuation'!$F$5-Assumptions!$B$23-Assumptions!$B$31+Assumptions!$B$32)/Assumptions!$B$35 -> 72.137367 | F5: =(SUMPRODUCT('DCF Valuation'!$B$4:$F$4/(1+$A5)^'DCF Valuation'!$B$5:$F$5)+'DCF Valuation'!$F$4*(1+F$4)/($A5-F$4)/(1+$A5)^'DCF Valuation'!$F$5-Assumptions!$B$23-Assumptions!$B$31+Assumptions!$B$32)/Assumptions!$B$35 -> 83.302596
A6: =Assumptions!$B$25+(1-3)*0.005 -> 0.072 | B6: =(SUMPRODUCT('DCF Valuation'!$B$4:$F$4/(1+$A6)^'DCF Valuation'!$B$5:$F$5)+'DCF Valuation'!$F$4*(1+B$4)/($A6-B$4)/(1+$A6)^'DCF Valuation'!$F$5-Assumptions!$B$23-Assumptions!$B$31+Assumptions!$B$32)/Assumptions!$B$35 -> 46.089002 | C6: =(SUMPRODUCT('DCF Valuation'!$B$4:$F$4/(1+$A6)^'DCF Valuation'!$B$5:$F$5)+'DCF Valuation'!$F$4*(1+C$4)/($A6-C$4)/(1+$A6)^'DCF Valuation'!$F$5-Assumptions!$B$23-Assumptions!$B$31+Assumptions!$B$32)/Assumptions!$B$35 -> 50.466437 | D6: =(SUMPRODUCT('DCF Valuation'!$B$4:$F$4/(1+$A6)^'DCF Valuation'!$B$5:$F$5)+'DCF Valuation'!$F$4*(1+D$4)/($A6-D$4)/(1+$A6)^'DCF Valuation'!$F$5-Assumptions!$B$23-Assumptions!$B$31+Assumptions!$B$32)/Assumptions!$B$35 -> 55.77524 | E6: =(SUMPRODUCT('DCF Valuation'!$B$4:$F$4/(1+$A6)^'DCF Valuation'!$B$5:$F$5)+'DCF Valuation'!$F$4*(1+E$4)/($A6-E$4)/(1+$A6)^'DCF Valuation'!$F$5-Assumptions!$B$23-Assumptions!$B$31+Assumptions!$B$32)/Assumptions!$B$35 -> 62.348044 | F6: =(SUMPRODUCT('DCF Valuation'!$B$4:$F$4/(1+$A6)^'DCF Valuation'!$B$5:$F$5)+'DCF Valuation'!$F$4*(1+F$4)/($A6-F$4)/(1+$A6)^'DCF Valuation'!$F$5-Assumptions!$B$23-Assumptions!$B$31+Assumptions!$B$32)/Assumptions!$B$35 -> 70.697282
A7: =Assumptions!$B$25+(2-3)*0.005 -> 0.077 | B7: =(SUMPRODUCT('DCF Valuation'!$B$4:$F$4/(1+$A7)^'DCF Valuation'!$B$5:$F$5)+'DCF Valuation'!$F$4*(1+B$4)/($A7-B$4)/(1+$A7)^'DCF Valuation'!$F$5-Assumptions!$B$23-Assumptions!$B$31+Assumptions!$B$32)/Assumptions!$B$35 -> 41.531691 | C7: =(SUMPRODUCT('DCF Valuation'!$B$4:$F$4/(1+$A7)^'DCF Valuation'!$B$5:$F$5)+'DCF Valuation'!$F$4*(1+C$4)/($A7-C$4)/(1+$A7)^'DCF Valuation'!$F$5-Assumptions!$B$23-Assumptions!$B$31+Assumptions!$B$32)/Assumptions!$B$35 -> 45.135383 | D7: =(SUMPRODUCT('DCF Valuation'!$B$4:$F$4/(1+$A7)^'DCF Valuation'!$B$5:$F$5)+'DCF Valuation'!$F$4*(1+D$4)/($A7-D$4)/(1+$A7)^'DCF Valuation'!$F$5-Assumptions!$B$23-Assumptions!$B$31+Assumptions!$B$32)/Assumptions!$B$35 -> 49.432092 | E7: =(SUMPRODUCT('DCF Valuation'!$B$4:$F$4/(1+$A7)^'DCF Valuation'!$B$5:$F$5)+'DCF Valuation'!$F$4*(1+E$4)/($A7-E$4)/(1+$A7)^'DCF Valuation'!$F$5-Assumptions!$B$23-Assumptions!$B$31+Assumptions!$B$32)/Assumptions!$B$35 -> 54.642995 | F7: =(SUMPRODUCT('DCF Valuation'!$B$4:$F$4/(1+$A7)^'DCF Valuation'!$B$5:$F$5)+'DCF Valuation'!$F$4*(1+F$4)/($A7-F$4)/(1+$A7)^'DCF Valuation'!$F$5-Assumptions!$B$23-Assumptions!$B$31+Assumptions!$B$32)/Assumptions!$B$35 -> 61.094589
A8: =Assumptions!$B$25+(3-3)*0.005 -> 0.082 | B8: =(SUMPRODUCT('DCF Valuation'!$B$4:$F$4/(1+$A8)^'DCF Valuation'!$B$5:$F$5)+'DCF Valuation'!$F$4*(1+B$4)/($A8-B$4)/(1+$A8)^'DCF Valuation'!$F$5-Assumptions!$B$23-Assumptions!$B$31+Assumptions!$B$32)/Assumptions!$B$35 -> 37.656029 | C8: =(SUMPRODUCT('DCF Valuation'!$B$4:$F$4/(1+$A8)^'DCF Valuation'!$B$5:$F$5)+'DCF Valuation'!$F$4*(1+C$4)/($A8-C$4)/(1+$A8)^'DCF Valuation'!$F$5-Assumptions!$B$23-Assumptions!$B$31+Assumptions!$B$32)/Assumptions!$B$35 -> 40.665578 | D8: =(SUMPRODUCT('DCF Valuation'!$B$4:$F$4/(1+$A8)^'DCF Valuation'!$B$5:$F$5)+'DCF Valuation'!$F$4*(1+D$4)/($A8-D$4)/(1+$A8)^'DCF Valuation'!$F$5-Assumptions!$B$23-Assumptions!$B$31+Assumptions!$B$32)/Assumptions!$B$35 -> 44.203118 | E8: =(SUMPRODUCT('DCF Valuation'!$B$4:$F$4/(1+$A8)^'DCF Valuation'!$B$5:$F$5)+'DCF Valuation'!$F$4*(1+E$4)/($A8-E$4)/(1+$A8)^'DCF Valuation'!$F$5-Assumptions!$B$23-Assumptions!$B$31+Assumptions!$B$32)/Assumptions!$B$35 -> 48.420955 | F8: =(SUMPRODUCT('DCF Valuation'!$B$4:$F$4/(1+$A8)^'DCF Valuation'!$B$5:$F$5)+'DCF Valuation'!$F$4*(1+F$4)/($A8-F$4)/(1+$A8)^'DCF Valuation'!$F$5-Assumptions!$B$23-Assumptions!$B$31+Assumptions!$B$32)/Assumptions!$B$35 -> 53.536204
A9: =Assumptions!$B$25+(4-3)*0.005 -> 0.087 | B9: =(SUMPRODUCT('DCF Valuation'!$B$4:$F$4/(1+$A9)^'DCF Valuation'!$B$5:$F$5)+'DCF Valuation'!$F$4*(1+B$4)/($A9-B$4)/(1+$A9)^'DCF Valuation'!$F$5-Assumptions!$B$23-Assumptions!$B$31+Assumptions!$B$32)/Assumptions!$B$35 -> 34.319973 | C9: =(SUMPRODUCT('DCF Valuation'!$B$4:$F$4/(1+$A9)^'DCF Valuation'!$B$5:$F$5)+'DCF Valuation'!$F$4*(1+C$4)/($A9-C$4)/(1+$A9)^'DCF Valuation'!$F$5-Assumptions!$B$23-Assumptions!$B$31+Assumptions!$B$32)/Assumptions!$B$35 -> 36.864174 | D9: =(SUMPRODUCT('DCF Valuation'!$B$4:$F$4/(1+$A9)^'DCF Valuation'!$B$5:$F$5)+'DCF Valuation'!$F$4*(1+D$4)/($A9-D$4)/(1+$A9)^'DCF Valuation'!$F$5-Assumptions!$B$23-Assumptions!$B$31+Assumptions!$B$32)/Assumptions!$B$35 -> 39.818731 | E9: =(SUMPRODUCT('DCF Valuation'!$B$4:$F$4/(1+$A9)^'DCF Valuation'!$B$5:$F$5)+'DCF Valuation'!$F$4*(1+E$4)/($A9-E$4)/(1+$A9)^'DCF Valuation'!$F$5-Assumptions!$B$23-Assumptions!$B$31+Assumptions!$B$32)/Assumptions!$B$35 -> 43.291631 | F9: =(SUMPRODUCT('DCF Valuation'!$B$4:$F$4/(1+$A9)^'DCF Valuation'!$B$5:$F$5)+'DCF Valuation'!$F$4*(1+F$4)/($A9-F$4)/(1+$A9)^'DCF Valuation'!$F$5-Assumptions!$B$23-Assumptions!$B$31+Assumptions!$B$32)/Assumptions!$B$35 -> 47.432396
A10: =Assumptions!$B$25+(5-3)*0.005 -> 0.092 | B10: =(SUMPRODUCT('DCF Valuation'!$B$4:$F$4/(1+$A10)^'DCF Valuation'!$B$5:$F$5)+'DCF Valuation'!$F$4*(1+B$4)/($A10-B$4)/(1+$A10)^'DCF Valuation'!$F$5-Assumptions!$B$23-Assumptions!$B$31+Assumptions!$B$32)/Assumptions!$B$35 -> 31.418376 | C10: =(SUMPRODUCT('DCF Valuation'!$B$4:$F$4/(1+$A10)^'DCF Valuation'!$B$5:$F$5)+'DCF Valuation'!$F$4*(1+C$4)/($A10-C$4)/(1+$A10)^'DCF Valuation'!$F$5-Assumptions!$B$23-Assumptions!$B$31+Assumptions!$B$32)/Assumptions!$B$35 -> 33.591893 | D10: =(SUMPRODUCT('DCF Valuation'!$B$4:$F$4/(1+$A10)^'DCF Valuation'!$B$5:$F$5)+'DCF Valuation'!$F$4*(1+D$4)/($A10-D$4)/(1+$A10)^'DCF Valuation'!$F$5-Assumptions!$B$23-Assumptions!$B$31+Assumptions!$B$32)/Assumptions!$B$35 -> 36.089817 | E10: =(SUMPRODUCT('DCF Valuation'!$B$4:$F$4/(1+$A10)^'DCF Valuation'!$B$5:$F$5)+'DCF Valuation'!$F$4*(1+E$4)/($A10-E$4)/(1+$A10)^'DCF Valuation'!$F$5-Assumptions!$B$23-Assumptions!$B$31+Assumptions!$B$32)/Assumptions!$B$35 -> 38.990631 | F10: =(SUMPRODUCT('DCF Valuation'!$B$4:$F$4/(1+$A10)^'DCF Valuation'!$B$5:$F$5)+'DCF Valuation'!$F$4*(1+F$4)/($A10-F$4)/(1+$A10)^'DCF Valuation'!$F$5-Assumptions!$B$23-Assumptions!$B$31+Assumptions!$B$32)/Assumptions!$B$35 -> 42.400361
A11: =Assumptions!$B$25+(6-3)*0.005 -> 0.097 | B11: =(SUMPRODUCT('DCF Valuation'!$B$4:$F$4/(1+$A11)^'DCF Valuation'!$B$5:$F$5)+'DCF Valuation'!$F$4*(1+B$4)/($A11-B$4)/(1+$A11)^'DCF Valuation'!$F$5-Assumptions!$B$23-Assumptions!$B$31+Assumptions!$B$32)/Assumptions!$B$35 -> 28.871736 | C11: =(SUMPRODUCT('DCF Valuation'!$B$4:$F$4/(1+$A11)^'DCF Valuation'!$B$5:$F$5)+'DCF Valuation'!$F$4*(1+C$4)/($A11-C$4)/(1+$A11)^'DCF Valuation'!$F$5-Assumptions!$B$23-Assumptions!$B$31+Assumptions!$B$32)/Assumptions!$B$35 -> 30.745634 | D11: =(SUMPRODUCT('DCF Valuation'!$B$4:$F$4/(1+$A11)^'DCF Valuation'!$B$5:$F$5)+'DCF Valuation'!$F$4*(1+D$4)/($A11-D$4)/(1+$A11)^'DCF Valuation'!$F$5-Assumptions!$B$23-Assumptions!$B$31+Assumptions!$B$32)/Assumptions!$B$35 -> 32.879795 | E11: =(SUMPRODUCT('DCF Valuation'!$B$4:$F$4/(1+$A11)^'DCF Valuation'!$B$5:$F$5)+'DCF Valuation'!$F$4*(1+E$4)/($A11-E$4)/(1+$A11)^'DCF Valuation'!$F$5-Assumptions!$B$23-Assumptions!$B$31+Assumptions!$B$32)/Assumptions!$B$35 -> 35.332488 | F11: =(SUMPRODUCT('DCF Valuation'!$B$4:$F$4/(1+$A11)^'DCF Valuation'!$B$5:$F$5)+'DCF Valuation'!$F$4*(1+F$4)/($A11-F$4)/(1+$A11)^'DCF Valuation'!$F$5-Assumptions!$B$23-Assumptions!$B$31+Assumptions!$B$32)/Assumptions!$B$35 -> 38.180777
A14: TABLE 2: EXIT MULTIPLE — WACC VS EXIT EV/EBITDA
A15: WACC \ Multiple | B15: =Assumptions!$B$29+(0-2)*1 -> 10 | C15: =Assumptions!$B$29+(1-2)*1 -> 11 | D15: =Assumptions!$B$29+(2-2)*1 -> 12 | E15: =Assumptions!$B$29+(3-2)*1 -> 13 | F15: =Assumptions!$B$29+(4-2)*1 -> 14
A16: =Assumptions!$B$25+(0-3)*0.005 -> 0.067 | B16: =(SUMPRODUCT('DCF Valuation'!$B$4:$F$4/(1+$A16)^'DCF Valuation'!$B$5:$F$5)+'DCF Valuation'!$B$32*B$15/(1+$A16)^'DCF Valuation'!$F$5-Assumptions!$B$23-Assumptions!$B$31+Assumptions!$B$32)/Assumptions!$B$35 -> 41.841636 | C16: =(SUMPRODUCT('DCF Valuation'!$B$4:$F$4/(1+$A16)^'DCF Valuation'!$B$5:$F$5)+'DCF Valuation'!$B$32*C$15/(1+$A16)^'DCF Valuation'!$F$5-Assumptions!$B$23-Assumptions!$B$31+Assumptions!$B$32)/Assumptions!$B$35 -> 45.710019 | D16: =(SUMPRODUCT('DCF Valuation'!$B$4:$F$4/(1+$A16)^'DCF Valuation'!$B$5:$F$5)+'DCF Valuation'!$B$32*D$15/(1+$A16)^'DCF Valuation'!$F$5-Assumptions!$B$23-Assumptions!$B$31+Assumptions!$B$32)/Assumptions!$B$35 -> 49.578401 | E16: =(SUMPRODUCT('DCF Valuation'!$B$4:$F$4/(1+$A16)^'DCF Valuation'!$B$5:$F$5)+'DCF Valuation'!$B$32*E$15/(1+$A16)^'DCF Valuation'!$F$5-Assumptions!$B$23-Assumptions!$B$31+Assumptions!$B$32)/Assumptions!$B$35 -> 53.446784 | F16: =(SUMPRODUCT('DCF Valuation'!$B$4:$F$4/(1+$A16)^'DCF Valuation'!$B$5:$F$5)+'DCF Valuation'!$B$32*F$15/(1+$A16)^'DCF Valuation'!$F$5-Assumptions!$B$23-Assumptions!$B$31+Assumptions!$B$32)/Assumptions!$B$35 -> 57.315166
A17: =Assumptions!$B$25+(1-3)*0.005 -> 0.072 | B17: =(SUMPRODUCT('DCF Valuation'!$B$4:$F$4/(1+$A17)^'DCF Valuation'!$B$5:$F$5)+'DCF Valuation'!$B$32*B$15/(1+$A17)^'DCF Valuation'!$F$5-Assumptions!$B$23-Assumptions!$B$31+Assumptions!$B$32)/Assumptions!$B$35 -> 40.774399 | C17: =(SUMPRODUCT('DCF Valuation'!$B$4:$F$4/(1+$A17)^'DCF Valuation'!$B$5:$F$5)+'DCF Valuation'!$B$32*C$15/(1+$A17)^'DCF Valuation'!$F$5-Assumptions!$B$23-Assumptions!$B$31+Assumptions!$B$32)/Assumptions!$B$35 -> 44.553405 | D17: =(SUMPRODUCT('DCF Valuation'!$B$4:$F$4/(1+$A17)^'DCF Valuation'!$B$5:$F$5)+'DCF Valuation'!$B$32*D$15/(1+$A17)^'DCF Valuation'!$F$5-Assumptions!$B$23-Assumptions!$B$31+Assumptions!$B$32)/Assumptions!$B$35 -> 48.332411 | E17: =(SUMPRODUCT('DCF Valuation'!$B$4:$F$4/(1+$A17)^'DCF Valuation'!$B$5:$F$5)+'DCF Valuation'!$B$32*E$15/(1+$A17)^'DCF Valuation'!$F$5-Assumptions!$B$23-Assumptions!$B$31+Assumptions!$B$32)/Assumptions!$B$35 -> 52.111417 | F17: =(SUMPRODUCT('DCF Valuation'!$B$4:$F$4/(1+$A17)^'DCF Valuation'!$B$5:$F$5)+'DCF Valuation'!$B$32*F$15/(1+$A17)^'DCF Valuation'!$F$5-Assumptions!$B$23-Assumptions!$B$31+Assumptions!$B$32)/Assumptions!$B$35 -> 55.890423
A18: =Assumptions!$B$25+(2-3)*0.005 -> 0.077 | B18: =(SUMPRODUCT('DCF Valuation'!$B$4:$F$4/(1+$A18)^'DCF Valuation'!$B$5:$F$5)+'DCF Valuation'!$B$32*B$15/(1+$A18)^'DCF Valuation'!$F$5-Assumptions!$B$23-Assumptions!$B$31+Assumptions!$B$32)/Assumptions!$B$35 -> 39.735551 | C18: =(SUMPRODUCT('DCF Valuation'!$B$4:$F$4/(1+$A18)^'DCF Valuation'!$B$5:$F$5)+'DCF Valuation'!$B$32*C$15/(1+$A18)^'DCF Valuation'!$F$5-Assumptions!$B$23-Assumptions!$B$31+Assumptions!$B$32)/Assumptions!$B$35 -> 43.427647 | D18: =(SUMPRODUCT('DCF Valuation'!$B$4:$F$4/(1+$A18)^'DCF Valuation'!$B$5:$F$5)+'DCF Valuation'!$B$32*D$15/(1+$A18)^'DCF Valuation'!$F$5-Assumptions!$B$23-Assumptions!$B$31+Assumptions!$B$32)/Assumptions!$B$35 -> 47.119742 | E18: =(SUMPRODUCT('DCF Valuation'!$B$4:$F$4/(1+$A18)^'DCF Valuation'!$B$5:$F$5)+'DCF Valuation'!$B$32*E$15/(1+$A18)^'DCF Valuation'!$F$5-Assumptions!$B$23-Assumptions!$B$31+Assumptions!$B$32)/Assumptions!$B$35 -> 50.811838 | F18: =(SUMPRODUCT('DCF Valuation'!$B$4:$F$4/(1+$A18)^'DCF Valuation'!$B$5:$F$5)+'DCF Valuation'!$B$32*F$15/(1+$A18)^'DCF Valuation'!$F$5-Assumptions!$B$23-Assumptions!$B$31+Assumptions!$B$32)/Assumptions!$B$35 -> 54.503934
A19: =Assumptions!$B$25+(3-3)*0.005 -> 0.082 | B19: =(SUMPRODUCT('DCF Valuation'!$B$4:$F$4/(1+$A19)^'DCF Valuation'!$B$5:$F$5)+'DCF Valuation'!$B$32*B$15/(1+$A19)^'DCF Valuation'!$F$5-Assumptions!$B$23-Assumptions!$B$31+Assumptions!$B$32)/Assumptions!$B$35 -> 38.724198 | C19: =(SUMPRODUCT('DCF Valuation'!$B$4:$F$4/(1+$A19)^'DCF Valuation'!$B$5:$F$5)+'DCF Valuation'!$B$32*C$15/(1+$A19)^'DCF Valuation'!$F$5-Assumptions!$B$23-Assumptions!$B$31+Assumptions!$B$32)/Assumptions!$B$35 -> 42.331771 | D19: =(SUMPRODUCT('DCF Valuation'!$B$4:$F$4/(1+$A19)^'DCF Valuation'!$B$5:$F$5)+'DCF Valuation'!$B$32*D$15/(1+$A19)^'DCF Valuation'!$F$5-Assumptions!$B$23-Assumptions!$B$31+Assumptions!$B$32)/Assumptions!$B$35 -> 45.939345 | E19: =(SUMPRODUCT('DCF Valuation'!$B$4:$F$4/(1+$A19)^'DCF Valuation'!$B$5:$F$5)+'DCF Valuation'!$B$32*E$15/(1+$A19)^'DCF Valuation'!$F$5-Assumptions!$B$23-Assumptions!$B$31+Assumptions!$B$32)/Assumptions!$B$35 -> 49.546918 | F19: =(SUMPRODUCT('DCF Valuation'!$B$4:$F$4/(1+$A19)^'DCF Valuation'!$B$5:$F$5)+'DCF Valuation'!$B$32*F$15/(1+$A19)^'DCF Valuation'!$F$5-Assumptions!$B$23-Assumptions!$B$31+Assumptions!$B$32)/Assumptions!$B$35 -> 53.154492
A20: =Assumptions!$B$25+(4-3)*0.005 -> 0.087 | B20: =(SUMPRODUCT('DCF Valuation'!$B$4:$F$4/(1+$A20)^'DCF Valuation'!$B$5:$F$5)+'DCF Valuation'!$B$32*B$15/(1+$A20)^'DCF Valuation'!$F$5-Assumptions!$B$23-Assumptions!$B$31+Assumptions!$B$32)/Assumptions!$B$35 -> 37.73948 | C20: =(SUMPRODUCT('DCF Valuation'!$B$4:$F$4/(1+$A20)^'DCF Valuation'!$B$5:$F$5)+'DCF Valuation'!$B$32*C$15/(1+$A20)^'DCF Valuation'!$F$5-Assumptions!$B$23-Assumptions!$B$31+Assumptions!$B$32)/Assumptions!$B$35 -> 41.264843 | D20: =(SUMPRODUCT('DCF Valuation'!$B$4:$F$4/(1+$A20)^'DCF Valuation'!$B$5:$F$5)+'DCF Valuation'!$B$32*D$15/(1+$A20)^'DCF Valuation'!$F$5-Assumptions!$B$23-Assumptions!$B$31+Assumptions!$B$32)/Assumptions!$B$35 -> 44.790205 | E20: =(SUMPRODUCT('DCF Valuation'!$B$4:$F$4/(1+$A20)^'DCF Valuation'!$B$5:$F$5)+'DCF Valuation'!$B$32*E$15/(1+$A20)^'DCF Valuation'!$F$5-Assumptions!$B$23-Assumptions!$B$31+Assumptions!$B$32)/Assumptions!$B$35 -> 48.315568 | F20: =(SUMPRODUCT('DCF Valuation'!$B$4:$F$4/(1+$A20)^'DCF Valuation'!$B$5:$F$5)+'DCF Valuation'!$B$32*F$15/(1+$A20)^'DCF Valuation'!$F$5-Assumptions!$B$23-Assumptions!$B$31+Assumptions!$B$32)/Assumptions!$B$35 -> 51.84093
A21: =Assumptions!$B$25+(5-3)*0.005 -> 0.092 | B21: =(SUMPRODUCT('DCF Valuation'!$B$4:$F$4/(1+$A21)^'DCF Valuation'!$B$5:$F$5)+'DCF Valuation'!$B$32*B$15/(1+$A21)^'DCF Valuation'!$F$5-Assumptions!$B$23-Assumptions!$B$31+Assumptions!$B$32)/Assumptions!$B$35 -> 36.780568 | C21: =(SUMPRODUCT('DCF Valuation'!$B$4:$F$4/(1+$A21)^'DCF Valuation'!$B$5:$F$5)+'DCF Valuation'!$B$32*C$15/(1+$A21)^'DCF Valuation'!$F$5-Assumptions!$B$23-Assumptions!$B$31+Assumptions!$B$32)/Assumptions!$B$35 -> 40.225957 | D21: =(SUMPRODUCT('DCF Valuation'!$B$4:$F$4/(1+$A21)^'DCF Valuation'!$B$5:$F$5)+'DCF Valuation'!$B$32*D$15/(1+$A21)^'DCF Valuation'!$F$5-Assumptions!$B$23-Assumptions!$B$31+Assumptions!$B$32)/Assumptions!$B$35 -> 43.671347 | E21: =(SUMPRODUCT('DCF Valuation'!$B$4:$F$4/(1+$A21)^'DCF Valuation'!$B$5:$F$5)+'DCF Valuation'!$B$32*E$15/(1+$A21)^'DCF Valuation'!$F$5-Assumptions!$B$23-Assumptions!$B$31+Assumptions!$B$32)/Assumptions!$B$35 -> 47.116736 | F21: =(SUMPRODUCT('DCF Valuation'!$B$4:$F$4/(1+$A21)^'DCF Valuation'!$B$5:$F$5)+'DCF Valuation'!$B$32*F$15/(1+$A21)^'DCF Valuation'!$F$5-Assumptions!$B$23-Assumptions!$B$31+Assumptions!$B$32)/Assumptions!$B$35 -> 50.562125
A22: =Assumptions!$B$25+(6-3)*0.005 -> 0.097 | B22: =(SUMPRODUCT('DCF Valuation'!$B$4:$F$4/(1+$A22)^'DCF Valuation'!$B$5:$F$5)+'DCF Valuation'!$B$32*B$15/(1+$A22)^'DCF Valuation'!$F$5-Assumptions!$B$23-Assumptions!$B$31+Assumptions!$B$32)/Assumptions!$B$35 -> 35.846661 | C22: =(SUMPRODUCT('DCF Valuation'!$B$4:$F$4/(1+$A22)^'DCF Valuation'!$B$5:$F$5)+'DCF Valuation'!$B$32*C$15/(1+$A22)^'DCF Valuation'!$F$5-Assumptions!$B$23-Assumptions!$B$31+Assumptions!$B$32)/Assumptions!$B$35 -> 39.214245 | D22: =(SUMPRODUCT('DCF Valuation'!$B$4:$F$4/(1+$A22)^'DCF Valuation'!$B$5:$F$5)+'DCF Valuation'!$B$32*D$15/(1+$A22)^'DCF Valuation'!$F$5-Assumptions!$B$23-Assumptions!$B$31+Assumptions!$B$32)/Assumptions!$B$35 -> 42.581828 | E22: =(SUMPRODUCT('DCF Valuation'!$B$4:$F$4/(1+$A22)^'DCF Valuation'!$B$5:$F$5)+'DCF Valuation'!$B$32*E$15/(1+$A22)^'DCF Valuation'!$F$5-Assumptions!$B$23-Assumptions!$B$31+Assumptions!$B$32)/Assumptions!$B$35 -> 45.949411 | F22: =(SUMPRODUCT('DCF Valuation'!$B$4:$F$4/(1+$A22)^'DCF Valuation'!$B$5:$F$5)+'DCF Valuation'!$B$32*F$15/(1+$A22)^'DCF Valuation'!$F$5-Assumptions!$B$23-Assumptions!$B$31+Assumptions!$B$32)/Assumptions!$B$35 -> 49.316995
A24: Green = implied price above the market reference price in Assumptions B36. The centre cells (D8 and D19) use the main DCF WACC, terminal growth and exit multiple and therefore reconcile to the main valuation.

Sheet Review Notes
A1: REVIEW NOTES — MODEL CHECKS & CHANGES
A3: AUTOMATED CHECKS
A4: 1 | B4: Gordon sensitivity centre reconciles | C4: =IF(ABS('Sensitivity Analysis'!D8-'DCF Valuation'!B27)<0.01,"OK","CHECK") -> OK
A5: 2 | B5: Exit sensitivity centre reconciles | C5: =IF(ABS('Sensitivity Analysis'!D19-'DCF Valuation'!B38)<0.01,"OK","CHECK") -> OK
A6: 3 | B6: WACC > terminal growth | C6: =IF(Assumptions!B25>Assumptions!B28,"OK","CHECK") -> OK
A7: 4 | B7: FY2025 EBIT margin ties to reported 17.9% | C7: =IF(ABS('Income Statement & FCF'!B9-0.179)<0.0005,"OK","CHECK") -> OK
A9: KEY FIXES FROM THE PRIOR MODEL
A10: 1 | B10: Base year | C10: FY2025A continuing operations is now the actual starting point; FY2026E–FY2030E are forecasts.
A11: 2 | B11: Currency | C11: All DCF operating figures are converted from EUR into GBP; the source sheet retains the reported EUR figures.
A12: 3 | B12: EBIT | C12: The DCF starts from reported FY2025 EBIT / operating profit of €9,037m rather than an invented historical margin.
A13: 4 | B13: D&A / capex / NWC | C13: FY2025 actual D&A €1,310m, gross capex €1,591m and working-capital cash flow €116m are sourced from Unilever's 2025 reporting.
A14: 5 | B14: Net debt | C14: FY2025 net debt is €23,076m, converted at the year-end FX assumption — materially higher than the prior £9.8bn input.
A15: 6 | B15: Shares | C15: FY2025 year-end shares net of treasury = 2,179.5m after the share consolidation.
A16: 7 | B16: Terminal cross-check | C16: A full EV/EBITDA exit-multiple method and sensitivity table are included.
A17: 8 | B17: WACC | C17: The main DCF uses the requested 8.2% WACC as an explicit scenario input. A formula-based market WACC is shown separately rather than pretending it equals 8.2%.
A19: IMPORTANT JUDGEMENT CALLS
B20: WACC | C20: 8.2% is a user-selected scenario, not a mechanically derived result from the displayed CAPM inputs. This is deliberate and transparent.
B21: Forecast margins | C21: The EBIT margin rises from 17.9% to 18.7% over the forecast period; this is an analyst assumption.
B22: TMICC | C22: The retained TMICC stake is treated as a non-operating asset and added to equity value because it does not contribute to the operating FCF forecast.
B23: NCI | C23: NCI is deducted at its FY2025 book value rather than inventing a valuation multiple for minorities.
